{
  "date": "2026-02-09",
  "market": 18,
  "expansionId": 6445,
  "expansionName": "Egghead (Asia Region Legal)",
  "count": 32,
  "priceGuides": [
    {
      "idProduct": 865611,
      "idCategory": 1625,
      "avg": 30.82,
      "low": 39.99,
      "trend": 29.99,
      "avg1": null,
      "avg7": null,
      "avg30": null,
      "avg-foil": null,
      "low-foil": null,
      "trend-foil": 0,
      "avg1-foil": null,
      "avg7-foil": null,
      "avg30-foil": null,
      "productName": "Starter Deck: Egghead (Asia Region Legal)",
      "productCategoryName": "One Piece Preconstructed Decks"
    },
    {
      "idProduct": 867299,
      "idCategory": 1621,
      "avg": 8.85,
      "low": 2,
      "trend": 4.96,
      "avg1": 4.99,
      "avg7": 8.37,
      "avg30": 8.37,
      "avg-foil": null,
      "low-foil": null,
      "trend-foil": 0,
      "avg1-foil": null,
      "avg7-foil": null,
      "avg30-foil": null,
      "productName": "Monkey.D.Luffy (ST29-001)",
      "productCategoryName": "One Piece Single"
    },
    {
      "idProduct": 867300,
      "idCategory": 1621,
      "avg": 100,
      "low": 50,
      "trend": 100,
      "avg1": 100,
      "avg7": 100,
      "avg30": 100,
      "avg-foil": null,
      "low-foil": null,
      "trend-foil": 0,
      "avg1-foil": null,
      "avg7-foil": null,
      "avg30-foil": null,
      "productName": "Monkey.D.Luffy (ST29-001)",
      "productCategoryName": "One Piece Single"
    },
    {
      "idProduct": 867301,
      "idCategory": 1621,
      "avg": null,
      "low": 1,
      "trend": null,
      "avg1": null,
      "avg7": null,
      "avg30": null,
      "productName": "Usopp (ST29-002)",
      "productCategoryName": "One Piece Single"
    },
    {
      "idProduct": 867302,
      "idCategory": 1621,
      "avg": null,
      "low": 6,
      "trend": null,
      "avg1": null,
      "avg7": null,
      "avg30": null,
      "productName": "Usopp (ST29-002)",
      "productCategoryName": "One Piece Single"
    },
    {
      "idProduct": 867303,
      "idCategory": 1621,
      "avg": null,
      "low": 1,
      "trend": null,
      "avg1": null,
      "avg7": null,
      "avg30": null,
      "productName": "Kaku (ST29-003)",
      "productCategoryName": "One Piece Single"
    },
    {
      "idProduct": 867304,
      "idCategory": 1621,
      "avg": null,
      "low": 14.89,
      "trend": null,
      "avg1": null,
      "avg7": null,
      "avg30": null,
      "productName": "Kaku (ST29-003)",
      "productCategoryName": "One Piece Single"
    },
    {
      "idProduct": 867305,
      "idCategory": 1621,
      "avg": 4.99,
      "low": 3.5,
      "trend": 4.99,
      "avg1": 4.99,
      "avg7": 4.99,
      "avg30": 4.99,
      "avg-foil": null,
      "low-foil": null,
      "trend-foil": 0,
      "avg1-foil": null,
      "avg7-foil": null,
      "avg30-foil": null,
      "productName": "Sanji (ST29-004)",
      "productCategoryName": "One Piece Single"
    },
    {
      "idProduct": 867306,
      "idCategory": 1621,
      "avg": null,
      "low": 39.99,
      "trend": null,
      "avg1": null,
      "avg7": null,
      "avg30": null,
      "productName": "Sanji (ST29-004)",
      "productCategoryName": "One Piece Single"
    },
    {
      "idProduct": 867307,
      "idCategory": 1621,
      "avg": null,
      "low": 1,
      "trend": null,
      "avg1": null,
      "avg7": null,
      "avg30": null,
      "productName": "Jinbe (ST29-005)",
      "productCategoryName": "One Piece Single"
    },
    {
      "idProduct": 867308,
      "idCategory": 1621,
      "avg": null,
      "low": 14.99,
      "trend": null,
      "avg1": null,
      "avg7": null,
      "avg30": null,
      "productName": "Jinbe (ST29-005)",
      "productCategoryName": "One Piece Single"
    },
    {
      "idProduct": 867309,
      "idCategory": 1621,
      "avg": null,
      "low": 1,
      "trend": null,
      "avg1": null,
      "avg7": null,
      "avg30": null,
      "productName": "Stussy (ST29-006)",
      "productCategoryName": "One Piece Single"
    },
    {
      "idProduct": 867310,
      "idCategory": 1621,
      "avg": null,
      "low": null,
      "trend": null,
      "avg1": null,
      "avg7": null,
      "avg30": null,
      "productName": "Stussy (ST29-006)",
      "productCategoryName": "One Piece Single"
    },
    {
      "idProduct": 867311,
      "idCategory": 1621,
      "avg": null,
      "low": 4,
      "trend": null,
      "avg1": null,
      "avg7": null,
      "avg30": null,
      "productName": "Tony Tony.Chopper (ST29-007)",
      "productCategoryName": "One Piece Single"
    },
    {
      "idProduct": 867312,
      "idCategory": 1621,
      "avg": null,
      "low": 6,
      "trend": null,
      "avg1": null,
      "avg7": null,
      "avg30": null,
      "productName": "Tony Tony.Chopper (ST29-007)",
      "productCategoryName": "One Piece Single"
    },
    {
      "idProduct": 867313,
      "idCategory": 1621,
      "avg": null,
      "low": 5,
      "trend": null,
      "avg1": null,
      "avg7": null,
      "avg30": null,
      "productName": "Nami (ST29-008)",
      "productCategoryName": "One Piece Single"
    },
    {
      "idProduct": 867314,
      "idCategory": 1621,
      "avg": 39.99,
      "low": 25,
      "trend": 26.57,
      "avg1": 29,
      "avg7": 31.33,
      "avg30": 31.33,
      "avg-foil": null,
      "low-foil": null,
      "trend-foil": 0,
      "avg1-foil": null,
      "avg7-foil": null,
      "avg30-foil": null,
      "productName": "Nami (ST29-008)",
      "productCategoryName": "One Piece Single"
    },
    {
      "idProduct": 867315,
      "idCategory": 1621,
      "avg": null,
      "low": 5,
      "trend": null,
      "avg1": null,
      "avg7": null,
      "avg30": null,
      "productName": "Nico Robin (ST29-009)",
      "productCategoryName": "One Piece Single"
    },
    {
      "idProduct": 867316,
      "idCategory": 1621,
      "avg": 22,
      "low": 31.5,
      "trend": 32,
      "avg1": 32,
      "avg7": 22,
      "avg30": 22,
      "avg-foil": null,
      "low-foil": null,
      "trend-foil": 0,
      "avg1-foil": null,
      "avg7-foil": null,
      "avg30-foil": null,
      "productName": "Nico Robin (ST29-009)",
      "productCategoryName": "One Piece Single"
    },
    {
      "idProduct": 867317,
      "idCategory": 1621,
      "avg": null,
      "low": 1,
      "trend": null,
      "avg1": null,
      "avg7": null,
      "avg30": null,
      "productName": "Franky (ST29-010)",
      "productCategoryName": "One Piece Single"
    },
    {
      "idProduct": 867318,
      "idCategory": 1621,
      "avg": null,
      "low": 14,
      "trend": null,
      "avg1": null,
      "avg7": null,
      "avg30": null,
      "productName": "Franky (ST29-010)",
      "productCategoryName": "One Piece Single"
    },
    {
      "idProduct": 867319,
      "idCategory": 1621,
      "avg": null,
      "low": 1,
      "trend": null,
      "avg1": null,
      "avg7": null,
      "avg30": null,
      "productName": "Brook (ST29-011)",
      "productCategoryName": "One Piece Single"
    },
    {
      "idProduct": 867320,
      "idCategory": 1621,
      "avg": null,
      "low": 13.99,
      "trend": null,
      "avg1": null,
      "avg7": null,
      "avg30": null,
      "productName": "Brook (ST29-011)",
      "productCategoryName": "One Piece Single"
    },
    {
      "idProduct": 867321,
      "idCategory": 1621,
      "avg": null,
      "low": 1,
      "trend": null,
      "avg1": null,
      "avg7": null,
      "avg30": null,
      "productName": "Monkey.D.Luffy (ST29-012)",
      "productCategoryName": "One Piece Single"
    },
    {
      "idProduct": 867322,
      "idCategory": 1621,
      "avg": 14.99,
      "low": 14.99,
      "trend": 14.99,
      "avg1": 14.99,
      "avg7": 14.99,
      "avg30": 14.99,
      "avg-foil": null,
      "low-foil": null,
      "trend-foil": 0,
      "avg1-foil": null,
      "avg7-foil": null,
      "avg30-foil": null,
      "productName": "Monkey.D.Luffy (ST29-012)",
      "productCategoryName": "One Piece Single"
    },
    {
      "idProduct": 867323,
      "idCategory": 1621,
      "avg": null,
      "low": 1,
      "trend": null,
      "avg1": null,
      "avg7": null,
      "avg30": null,
      "productName": "Rob Lucci (ST29-013)",
      "productCategoryName": "One Piece Single"
    },
    {
      "idProduct": 867324,
      "idCategory": 1621,
      "avg": null,
      "low": 13.99,
      "trend": null,
      "avg1": null,
      "avg7": null,
      "avg30": null,
      "productName": "Rob Lucci (ST29-013)",
      "productCategoryName": "One Piece Single"
    },
    {
      "idProduct": 867325,
      "idCategory": 1621,
      "avg": 4.99,
      "low": 3,
      "trend": 4.99,
      "avg1": 4.99,
      "avg7": 4.99,
      "avg30": 4.99,
      "avg-foil": null,
      "low-foil": null,
      "trend-foil": 0,
      "avg1-foil": null,
      "avg7-foil": null,
      "avg30-foil": null,
      "productName": "Roronoa Zoro (ST29-014)",
      "productCategoryName": "One Piece Single"
    },
    {
      "idProduct": 867326,
      "idCategory": 1621,
      "avg": null,
      "low": 19.99,
      "trend": null,
      "avg1": null,
      "avg7": null,
      "avg30": null,
      "productName": "Roronoa Zoro (ST29-014)",
      "productCategoryName": "One Piece Single"
    },
    {
      "idProduct": 867327,
      "idCategory": 1621,
      "avg": null,
      "low": 1,
      "trend": null,
      "avg1": null,
      "avg7": null,
      "avg30": null,
      "productName": "Raw Heat Strike (ST29-015)",
      "productCategoryName": "One Piece Single"
    },
    {
      "idProduct": 867328,
      "idCategory": 1621,
      "avg": null,
      "low": 2,
      "trend": null,
      "avg1": null,
      "avg7": null,
      "avg30": null,
      "productName": "Kizaru!! Compared to Two Years Ago We're a Hundred Times Stronger Now!! (ST29-016)",
      "productCategoryName": "One Piece Single"
    },
    {
      "idProduct": 867329,
      "idCategory": 1621,
      "avg": null,
      "low": 1,
      "trend": null,
      "avg1": null,
      "avg7": null,
      "avg30": null,
      "productName": "Iai Death Lion Song (ST29-017)",
      "productCategoryName": "One Piece Single"
    }
  ]
}